Workbook

Sheet 方案总览
B2: 积分定价方案总览（客户版 V3 · 2026-09-04）
B4: 一、计费规则（1积分＝1元面值）
B5: 计费项 | C5: 计费单位 | D5: 积分单价 | E5: 面值收入(元) | F5: 说明
B6: 视频生成 | C6: 条 | D6: =成本与毛利测算!$C$7 -> 30 | E6: =D6*成本与毛利测算!$C$6 -> 30 | F6: 主付费项，按成功成品计费
B7: 图片生成 | C7: 张 | D7: =成本与毛利测算!$C$10 -> 0.5 | E7: =D7*成本与毛利测算!$C$6 -> 0.5 | F7: 分镜首帧 / 人物形象图
B8: 视频分析 | C8: 次 | D8: =成本与毛利测算!$C$11 -> 1 | E8: =D8*成本与毛利测算!$C$6 -> 1 | F8: 参考视频 AI 拆解分镜
B10: 二、充值档位（充值送礼，多充多送）
B11: 档位 | C11: 充值金额(元) | D11: 赠送积分 | E11: 到账积分 | F11: 实际单价(元/积分) | G11: 相当于折扣 | H11: 状态
B12: 体验档 | C12: 500 | D12: 30 | E12: =C12+D12 -> 530 | F12: =IFERROR(C12/E12,0) -> 0.94339623 | G12: =F12/成本与毛利测算!$C$6 -> 0.94339623 | H12: 建议新增
B13: 标准档 | C13: 1000 | D13: 100 | E13: =C13+D13 -> 1100 | F13: =IFERROR(C13/E13,0) -> 0.90909091 | G13: =F13/成本与毛利测算!$C$6 -> 0.90909091 | H13: 已确认
B14: 高级档 | C14: 3000 | D14: 500 | E14: =C14+D14 -> 3500 | F14: =IFERROR(C14/E14,0) -> 0.85714286 | G14: =F14/成本与毛利测算!$C$6 -> 0.85714286 | H14: 已确认
B15: 铂金档 | C15: 5000 | D15: 1000 | E15: =C15+D15 -> 6000 | F15: =IFERROR(C15/E15,0) -> 0.83333333 | G15: =F15/成本与毛利测算!$C$6 -> 0.83333333 | H15: 建议新增
B16: 旗舰档 | C16: 10000 | D16: 2500 | E16: =C16+D16 -> 12500 | F16: =IFERROR(C16/E16,0) -> 0.8 | G16: =F16/成本与毛利测算!$C$6 -> 0.8 | H16: 建议新增
B18: 三、核心结论
B19: 1、积分锚定：1积分＝1元面值；充值赠送只稀释实际单价——标准档(1000送100)约0.909元/积分（9.1折），高级档(3000送500)约0.857元/积分（8.6折）。
B20: 2、单项毛利：视频生成毛利率约91%–95%；图片生成、视频分析单项毛利率约77%–80%。
B21: 3、单条成品视频全流程（视频分析1次＋图片8张＋视频生成1条）客户消耗约39积分；我方综合成本约3.9元，综合毛利率约88%–90%。
B22: 4、对比旧模式10元/次：单条成品毛利从约6.1元提升至约29.6–35.1元（约4.8–5.7倍），且按“条”计费、失败返还，对客户更透明。
B23: 5、建议配套规则：生成失败自动返还积分；积分有效期12个月；赠送积分与充值积分同池消耗、按下单先后扣减。
B25: 对外报价仅使用「一、计费规则」与「二、充值档位」；「三、核心结论」及成本测算表为内部资料，外发前请删除。

Sheet 成本与毛利测算
B2: 成本拆分与毛利测算（黄色假设项可调，全表联动）
B4: 一、基础参数（用户确认，勿随意改动）
B5: 参数 | C5: 数值 | D5: 单位 | E5: 来源说明
B6: 积分面值 | C6: 1 | D6: 元/积分 | E6: 用户确认：1积分=1元面值
B7: 视频生成积分单价 | C7: 30 | D7: 积分/条 | E7: 用户确认：30积分/条（原10元/次）
B8: 视频生成成本·768P | C8: 1.5 | D8: 元/条/15s | E8: 用户确认
B9: 视频生成成本·2K | C9: 2.5 | D9: 元/条/15s | E9: 用户确认
B10: 图片生成积分单价 | C10: 0.5 | D10: 积分/张 | E10: 用户确认：1积分/次
B11: 视频分析积分单价 | C11: 1 | D11: 积分/次 | E11: 用户确认：1积分/次
B13: 二、运营假设（可调整：改这里，全工作簿联动）
B14: 假设项 | C14: 数值 | D14: 单位 | E14: 说明
B15: 图片生成成本 | C15: 0.5 | D15: 元/张 | E15: 假设值，待按供应商账单校准
B16: 视频分析成本 | C16: 0.5 | D16: 元/次 | E16: 假设值，待按模型账单校准
B17: 单条视频平均图片张数 | C17: 3 | D17: 张/条 | E17: 按典型分镜首帧数估算
B18: 视频生成失败重试率 | C18: 0 | D18: — | E18: 失败重试成本由我方承担
B19: 768P 占比 | C19: 0.7 | D19: — | E19: 按客户用量结构估算
B20: 2K 占比 | C20: =1-C19 -> 0.3 | D20: — | E20: 自动计算 =1-768P占比
B22: 三、单条成品视频全流程测算（混合分辨率口径）
B23: 项目 | C23: 数值 | D23: 计算口径
B24: 视频混合成本(元/条) | C24: =C8*C19+C9*C20 -> 1.8 | D24: 768P成本×占比＋2K成本×占比
B25: 视频含重试成本(元/条) | C25: =C24*(1+C18) -> 1.8 | D25: 混合成本×(1＋重试率)
B26: 图片成本小计(元/条) | C26: =C17*C15 -> 1.5 | D26: 图片张数×图片成本
B27: 视频分析成本(元/条) | C27: =C16 -> 0.5 | D27: 每条分析1次
B28: 全流程总成本(元/条) | C28: =C25+C26+C27 -> 3.8 | D28: 视频＋图片＋分析
B29: 全流程消耗积分(积分/条) | C29: =C7+C17*C10+C11 -> 32.5 | D29: 生成30＋图片8×1＋分析1
B31: 四、单项售价-毛利测算（按充值档位）
B32: 计费项 | C32: 成本(元) | D32: 面值收入(元) | E32: 面值毛利(元) | F32: 面值毛利率 | G32: 1000档收入(元) | H32: 1000档毛利(元) | I32: 1000档毛利率 | J32: 3000档收入(元) | K32: 3000档毛利(元) | L32: 3000档毛利率
B33: 视频生成·768P | C33: =C8 -> 1.5 | D33: =$C$7*$C$6 -> 30 | E33: =D33-C33 -> 28.5 | F33: =IFERROR(E33/D33,0) -> 0.95 | G33: =$C$7*方案总览!$F$13 -> 27.272727 | H33: =G33-C33 -> 25.772727 | I33: =IFERROR(H33/G33,0) -> 0.945 | J33: =$C$7*方案总览!$F$14 -> 25.714286 | K33: =J33-C33 -> 24.214286 | L33: =IFERROR(K33/J33,0) -> 0.94166667
B34: 视频生成·2K | C34: =C9 -> 2.5 | D34: =$C$7*$C$6 -> 30 | E34: =D34-C34 -> 27.5 | F34: =IFERROR(E34/D34,0) -> 0.91666667 | G34: =$C$7*方案总览!$F$13 -> 27.272727 | H34: =G34-C34 -> 24.772727 | I34: =IFERROR(H34/G34,0) -> 0.90833333 | J34: =$C$7*方案总览!$F$14 -> 25.714286 | K34: =J34-C34 -> 23.214286 | L34: =IFERROR(K34/J34,0) -> 0.90277778
B35: 视频生成·混合 | C35: =C24 -> 1.8 | D35: =$C$7*$C$6 -> 30 | E35: =D35-C35 -> 28.2 | F35: =IFERROR(E35/D35,0) -> 0.94 | G35: =$C$7*方案总览!$F$13 -> 27.272727 | H35: =G35-C35 -> 25.472727 | I35: =IFERROR(H35/G35,0) -> 0.934 | J35: =$C$7*方案总览!$F$14 -> 25.714286 | K35: =J35-C35 -> 23.914286 | L35: =IFERROR(K35/J35,0) -> 0.93
B36: 图片生成 | C36: =C15 -> 0.5 | D36: =$C$10*$C$6 -> 0.5 | E36: =D36-C36 -> 0 | F36: =IFERROR(E36/D36,0) -> 0 | G36: =$C$10*方案总览!$F$13 -> 0.45454545 | H36: =G36-C36 -> -0.045454545 | I36: =IFERROR(H36/G36,0) -> -0.1 | J36: =$C$10*方案总览!$F$14 -> 0.42857143 | K36: =J36-C36 -> -0.071428571 | L36: =IFERROR(K36/J36,0) -> -0.16666667
B37: 视频分析 | C37: =C16 -> 0.5 | D37: =$C$11*$C$6 -> 1 | E37: =D37-C37 -> 0.5 | F37: =IFERROR(E37/D37,0) -> 0.5 | G37: =$C$11*方案总览!$F$13 -> 0.90909091 | H37: =G37-C37 -> 0.40909091 | I37: =IFERROR(H37/G37,0) -> 0.45 | J37: =$C$11*方案总览!$F$14 -> 0.85714286 | K37: =J37-C37 -> 0.35714286 | L37: =IFERROR(K37/J37,0) -> 0.41666667
B39: 内部资料：本表含供应商成本与运营假设，请勿直接发给客户；黄色口径以「运营假设」为准。

Sheet 新旧模式对比
B2: 新旧计费模式对比（单条成品视频口径）
B4: 一、计费口径变化
B5: 计费项 | C5: 旧模式 | D5: 新模式（积分制）
B6: 视频生成 | C6: 10元/次，失败重试重复扣费 | D6: 30积分/条，失败自动返还
B7: 图片生成 | C7: 未单独计费 | D7: 1积分/张
B8: 视频分析 | C8: 未单独计费 | D8: 1积分/次
B10: 二、单条成品视频经济性对比（混合分辨率，成本含15%重试）
B11: 模式 | C11: 客户消耗/支付 | D11: 我方实收(元) | E11: 我方成本(元) | F11: 单条毛利(元) | G11: 毛利率 | H11: 毛利倍数(vs旧)
B12: 旧模式 10元/次 | C12: 10 元/条（图片、分析不收费） | D12: 10 | E12: =成本与毛利测算!C28 -> 3.8 | F12: =D12-E12 -> 6.2 | G12: =IFERROR(F12/D12,0) -> 0.62 | H12: 1
B13: 新模式·面值 | C13: =TEXT(成本与毛利测算!C29,"0")&" 积分（≈等额面值）" -> 33 积分（≈等额面值） | D13: =成本与毛利测算!C29*成本与毛利测算!C6 -> 32.5 | E13: =成本与毛利测算!C28 -> 3.8 | F13: =D13-E13 -> 28.7 | G13: =IFERROR(F13/D13,0) -> 0.88307692 | H13: =IFERROR(F13/F$12,0) -> 4.6290323
B14: 新模式·标准档(1000送100) | C14: ="39 积分（赠送稀释后实收更低）" -> 39 积分（赠送稀释后实收更低） | D14: =成本与毛利测算!C29*方案总览!$F$13 -> 29.545455 | E14: =成本与毛利测算!C28 -> 3.8 | F14: =D14-E14 -> 25.745455 | G14: =IFERROR(F14/D14,0) -> 0.87138462 | H14: =IFERROR(F14/F$12,0) -> 4.1524927
B15: 新模式·高级档(3000送500) | C15: ="39 积分（赠送稀释后实收更低）" -> 39 积分（赠送稀释后实收更低） | D15: =成本与毛利测算!C29*方案总览!$F$14 -> 27.857143 | E15: =成本与毛利测算!C28 -> 3.8 | F15: =D15-E15 -> 24.057143 | G15: =IFERROR(F15/D15,0) -> 0.86358974 | H15: =IFERROR(F15/F$12,0) -> 3.8801843
B17: 三、单条毛利对比图
B18: 按当前参数联动刷新；口径见上表。
B42: 内部资料：含成本与毛利数据，请勿直接发给客户。

Sheet 客户销售统计表
B2: 客户销售成本统计表（按充值账期）
B4: 录入列：客户名称、充值日期、充值金额、赠送积分、四类用量；其余列自动计算。示例行（客户A/B/C）可直接覆盖。
B5: 客户名称 | C5: 充值日期 | D5: 充值金额(元) | E5: 赠送积分 | F5: 到账积分 | G5: 积分实际单价 | H5: 视频768P(条) | I5: 视频2K(条) | J5: 图片(张) | K5: 分析(次) | L5: 累计消耗积分 | M5: 剩余积分 | N5: 实收现金(元) | O5: 已确认收入(元) | P5: 实际成本(元) | Q5: 毛利(元) | R5: 毛利率 | S5: 备注
B6: 客户A（示例） | C6: 46249 | D6: 1000 | E6: 100 | F6: =D6+E6 -> 1100 | G6: =IFERROR(D6/F6,0) -> 0.90909091 | H6: 15 | I6: 5 | J6: 160 | K6: 20 | L6: =成本与毛利测算!$C$7*(H6+I6)+J6+K6 -> 780 | M6: =F6-L6 -> 320 | N6: =D6 -> 1000 | O6: =L6*G6 -> 709.09091 | P6: =(H6*成本与毛利测算!$C$8+I6*成本与毛利测算!$C$9)*(1+成本与毛利测算!$C$18)+J6*成本与毛利测算!$C$15+K6*成本与毛利测算!$C$16 -> 125 | Q6: =O6-P6 -> 584.09091 | R6: =IFERROR(Q6/O6,0) -> 0.82371795 | S6: 标准档
B7: 客户B（示例） | C7: 46254 | D7: 3000 | E7: 500 | F7: =D7+E7 -> 3500 | G7: =IFERROR(D7/F7,0) -> 0.85714286 | H7: 40 | I7: 30 | J7: 560 | K7: 70 | L7: =成本与毛利测算!$C$7*(H7+I7)+J7+K7 -> 2730 | M7: =F7-L7 -> 770 | N7: =D7 -> 3000 | O7: =L7*G7 -> 2340 | P7: =(H7*成本与毛利测算!$C$8+I7*成本与毛利测算!$C$9)*(1+成本与毛利测算!$C$18)+J7*成本与毛利测算!$C$15+K7*成本与毛利测算!$C$16 -> 450 | Q7: =O7-P7 -> 1890 | R7: =IFERROR(Q7/O7,0) -> 0.80769231 | S7: 高级档
B8: 客户C（示例） | C8: 46266 | D8: 500 | E8: 30 | F8: =D8+E8 -> 530 | G8: =IFERROR(D8/F8,0) -> 0.94339623 | H8: 6 | I8: 0 | J8: 48 | K8: 6 | L8: =成本与毛利测算!$C$7*(H8+I8)+J8+K8 -> 234 | M8: =F8-L8 -> 296 | N8: =D8 -> 500 | O8: =L8*G8 -> 220.75472 | P8: =(H8*成本与毛利测算!$C$8+I8*成本与毛利测算!$C$9)*(1+成本与毛利测算!$C$18)+J8*成本与毛利测算!$C$15+K8*成本与毛利测算!$C$16 -> 36 | Q8: =O8-P8 -> 184.75472 | R8: =IFERROR(Q8/O8,0) -> 0.83692308 | S8: 体验档
B9: 合计 | D9: =SUM(D6:D8) -> 4500 | E9: =SUM(E6:E8) -> 630 | F9: =SUM(F6:F8) -> 5130 | G9: =IFERROR(D9/F9,0) -> 0.87719298 | H9: =SUM(H6:H8) -> 61 | I9: =SUM(I6:I8) -> 35 | J9: =SUM(J6:J8) -> 768 | K9: =SUM(K6:K8) -> 96 | L9: =SUM(L6:L8) -> 3744 | M9: =F9-L9 -> 1386 | N9: =SUM(N6:N8) -> 4500 | O9: =SUM(O6:O8) -> 3269.8456 | P9: =SUM(P6:P8) -> 611 | Q9: =SUM(Q6:Q8) -> 2658.8456 | R9: =IFERROR(Q9/O9,0) -> 0.81314103
B11: 口径说明：「已确认收入」＝累计消耗积分×积分实际单价（与成本同期配比）；「实收现金」以充值金额为准，未消耗部分（剩余积分）为预收负债。
B12: 成本口径：视频成本含失败重试准备金（默认15%）；图片/分析成本为待校准假设，参数集中在「成本与毛利测算」表调整。
B13: 新增客户：在示例行下方插入行并下拉 F–R 列公式；「剩余积分」为负表示超耗，自动红色提示。
B15: 内部资料：含成本与毛利数据，请勿直接发给客户。

Sheet Review
A1: Check | B1: Expected | C1: Actual | D1: Status
A2: 客户统计-到账积分合计 | B2: =SUM(客户销售统计表!F6:F8) -> 5130 | C2: =客户销售统计表!F9 -> 5130 | D2: =IF(ABS(B2-C2)<0.01,"PASS","FAIL") -> PASS
A3: 客户统计-消耗积分合计 | B3: =SUM(客户销售统计表!L6:L8) -> 3744 | C3: =客户销售统计表!L9 -> 3744 | D3: =IF(ABS(B3-C3)<0.01,"PASS","FAIL") -> PASS
A4: 客户统计-毛利合计 | B4: =SUM(客户销售统计表!Q6:Q8) -> 2658.8456 | C4: =客户销售统计表!Q9 -> 2658.8456 | D4: =IF(ABS(B4-C4)<0.01,"PASS","FAIL") -> PASS
A5: 全流程消耗积分=39 | B5: =成本与毛利测算!C7+成本与毛利测算!C17*成本与毛利测算!C10+成本与毛利测算!C11 -> 32.5 | C5: =成本与毛利测算!C29 -> 32.5 | D5: =IF(ABS(B5-C5)<0.01,"PASS","FAIL") -> PASS
A6: 全流程总成本 | B6: =成本与毛利测算!C24*(1+成本与毛利测算!C18)+成本与毛利测算!C17*成本与毛利测算!C15+成本与毛利测算!C16 -> 3.8 | C6: =成本与毛利测算!C28 -> 3.8 | D6: =IF(ABS(B6-C6)<0.01,"PASS","FAIL") -> PASS
A7: 视频768P面值毛利 | B7: =成本与毛利测算!C7*成本与毛利测算!C6-成本与毛利测算!C8 -> 28.5 | C7: =成本与毛利测算!E33 -> 28.5 | D7: =IF(ABS(B7-C7)<0.01,"PASS","FAIL") -> PASS
A8: 对比表新模式面值毛利一致 | B8: =成本与毛利测算!C29*成本与毛利测算!C6-成本与毛利测算!C28 -> 28.7 | C8: =新旧模式对比!F13 -> 28.7 | D8: =IF(ABS(B8-C8)<0.01,"PASS","FAIL") -> PASS
